{
  "Name": "ListPickerFlyout",
  "Namespace": "Windows.UI.Xaml.Controls",
  "Interfaces": [
    {
      "Name": "IListPickerFlyout",
      "Namespace": "Windows.UI.Xaml.Controls",
      "GenericParameters": null,
      "IsArray": false,
      "IsReference": false
    }
  ],
  "Traits": [
    {
      "TraitType": "DirectActivation"
    },
    {
      "Interfaces": [
        {
          "Name": "IListPickerFlyoutStatics",
          "Namespace": "Windows.UI.Xaml.Controls"
        }
      ],
      "TraitType": "Static"
    },
    {
      "DefaultInterface": {
        "Name": "IListPickerFlyout",
        "Namespace": "Windows.UI.Xaml.Controls",
        "GenericParameters": null,
        "IsArray": false,
        "IsReference": false
      },
      "TraitType": "DefaultInterface"
    }
  ],
  "Type": "Class"
}